buzz/__init__.py
buzz/conc.py
buzz/constants.py
buzz/contents.py
buzz/corpus.py
buzz/dashview.py
buzz/dataset.py
buzz/file.py
buzz/html.py
buzz/parse.py
buzz/search.py
buzz/slice.py
buzz/table.py
buzz/tabview.py
buzz/tfidf.py
buzz/utils.py
buzz/views.py
buzz-3.0.6.data/scripts/parse
buzz-3.0.6.dist-info/LICENSE
buzz-3.0.6.dist-info/METADATA
buzz-3.0.6.dist-info/WHEEL
buzz-3.0.6.dist-info/top_level.txt
buzz-3.0.6.dist-info/RECORD
