Metadata-Version: 2.1
Name: buzz
Version: 3.0.6
Summary: Sophisticated corpus linguistics
Home-page: http://github.com/interrogator/buzz
Author: Daniel McDonald
Author-email: mcddjx@gmail.com
License: MIT
Keywords: corpus,linguistics,nlp
Platform: UNKNOWN
Requires-Dist: nltk
Requires-Dist: bllipparser
Requires-Dist: scipy
Requires-Dist: cython
Requires-Dist: depgrep (>=0.1.3)
Requires-Dist: scikit-learn
Requires-Dist: colorama
Requires-Dist: tensorflow (>=1.12.1)
Requires-Dist: setuptools (>=41.0.0)
Requires-Dist: spacy (==2.1.6)
Requires-Dist: pandas (==0.25.0)
Requires-Dist: tqdm (==4.33.0)
Requires-Dist: isort (==4.3.21)
Provides-Extra: word
Requires-Dist: buzzword (>=0.1.0) ; extra == 'word'
Requires-Dist: dash (==1.1.1) ; extra == 'word'
Requires-Dist: flask (==1.1.1) ; extra == 'word'
Requires-Dist: dash-core-components (==1.1.1) ; extra == 'word'
Requires-Dist: dash-html-components (==1.0.0) ; extra == 'word'
Requires-Dist: dash-renderer (==1.0.0) ; extra == 'word'
Requires-Dist: dash-table (==4.1.0) ; extra == 'word'
Requires-Dist: dash-daq (==0.1.7) ; extra == 'word'
